setup.py
ComponentDB_CLI.egg-info/PKG-INFO
ComponentDB_CLI.egg-info/SOURCES.txt
ComponentDB_CLI.egg-info/dependency_links.txt
ComponentDB_CLI.egg-info/entry_points.txt
ComponentDB_CLI.egg-info/requires.txt
ComponentDB_CLI.egg-info/top_level.txt
cdbCli/__init__.py
cdbCli/common/__init__.py
cdbCli/common/cli/__init__.py
cdbCli/common/cli/cliBase.py
cdbCli/common/utility/__init__.py
cdbCli/common/utility/configurationManager.py
cdbCli/service/__init__.py
cdbCli/service/cli/__init__.py
cdbCli/service/cli/cli.py
cdbCli/service/cli/cdbCliCmnds/__init__.py
cdbCli/service/cli/cdbCliCmnds/addDocumentFile.py
cdbCli/service/cli/cdbCliCmnds/addDocumentProperty.py
cdbCli/service/cli/cdbCliCmnds/addProperty.py
cdbCli/service/cli/cdbCliCmnds/cdb_log_to_mqtt.py
cdbCli/service/cli/cdbCliCmnds/createLocation.py
cdbCli/service/cli/cdbCliCmnds/getCatalogItemsByName.py
cdbCli/service/cli/cdbCliCmnds/getLocationIdByName.py
cdbCli/service/cli/cdbCliCmnds/getProperties.py
cdbCli/service/cli/cdbCliCmnds/help.py
cdbCli/service/cli/cdbCliCmnds/info.py
cdbCli/service/cli/cdbCliCmnds/search.py
cdbCli/service/cli/cdbCliCmnds/setItemDetails.py
cdbCli/service/cli/cdbCliCmnds/setItemLocation.py
cdbCli/service/cli/cdbCliCmnds/setItemLogById.py
cdbCli/service/cli/cdbCliCmnds/setItemStatusById.py
cdbCli/service/cli/cdbCliCmnds/setMachineInstallState.py
cdbCli/service/cli/cdbCliCmnds/setParentLocation.py
cdbCli/service/cli/cdbCliCmnds/setPropertiesAndMetadata.py
cdbCli/service/cli/cdbCliCmnds/setQrIdById.py
cdbCli/service/cli/cdbCliCmnds/updateHierarchy.py